my_package/__init__.py
my_package/models.py
my_package/views.py
pdp_django_package-0.1.0.dist-info/licenses/LICENSE
pdp_django_package-0.1.0.dist-info/METADATA
pdp_django_package-0.1.0.dist-info/WHEEL
pdp_django_package-0.1.0.dist-info/top_level.txt
pdp_django_package-0.1.0.dist-info/RECORD
