Metadata-Version: 2.4
Name: pdp-django-package
Version: 0.1.0
Summary: Add your description here
Home-page: https://pdp.uz
Author: Pdp academy
Author-email: Pdp <pdp@gmail.com>
Requires-Python: >=3.11
License-File: LICENSE
Requires-Dist: build>=1.2.2.post1
Requires-Dist: django>=5.2.3
Requires-Dist: setuptools>=80.9.0
Requires-Dist: twine>=6.1.0
Requires-Dist: wheel>=0.45.1
Dynamic: author
Dynamic: home-page
Dynamic: license-file
